pyworks_medialibrary/__init__.py
pyworks_medialibrary/config.py
pyworks_medialibrary/interfaces.py
pyworks_medialibrary/main.py
pyworks_medialibrary/s3_storage.py
pyworks_medialibrary/storage.py
pyworks_medialibrary-0.1.0.dist-info/LICENSE
pyworks_medialibrary-0.1.0.dist-info/WHEEL
pyworks_medialibrary-0.1.0.dist-info/METADATA
pyworks_medialibrary-0.1.0.dist-info/RECORD
