Metadata-Version: 2.1
Name: pyworks-medialibrary
Version: 0.1.0
Summary: Provide awsome tools for manage images and documents.
Home-page: https://github.com/pyworksasia/pyworks-medialibrary
License: MIT
Keywords: packaging,poetry
Author: PyWorks Asia Team
Author-email: opensource@pyworks.asia
Requires-Python: >=3.7,<4.0
Classifier: License :: OSI Approved :: MIT License
Classifier: Programming Language :: Python :: 3
Classifier: Programming Language :: Python :: 3.7
Classifier: Programming Language :: Python :: 3.8
Classifier: Programming Language :: Python :: 3.9
Requires-Dist: boto3 (>=1.17.17,<2.0.0)
Requires-Dist: pytest (>=6.2.2,<7.0.0)
Requires-Dist: pytest-cov (>=2.11.1,<3.0.0)
Requires-Dist: python-dotenv (>=0.15.0,<0.16.0)
Project-URL: Repository, https://github.com/pyworksasia/pyworks-medialibrary
